MANIFEST.in
README.md
setup.cfg
setup.py
cp_music/__init__.py
cp_music/cpm_model.py
cp_music/note.py
cp_music/utils.py
cp_music/xml.py
cp_music.egg-info/PKG-INFO
cp_music.egg-info/SOURCES.txt
cp_music.egg-info/dependency_links.txt
cp_music.egg-info/requires.txt
cp_music.egg-info/top_level.txt
examples/__init__.py
examples/example1.musicxml
examples/example1.py
tests/__init__.py
tests/tests.py