Metadata-Version: 2.1
Name: cp-music
Version: 0.0.1
Summary: A small library for constraint programming with musicxml in python using ortools
Home-page: https://github.com/CorbinMoon/cp-music
Author: Corbin Moon
Author-email: clangmoon@gmail.com
License: MIT
Project-URL: Source, https://github.com/CorbinMoon/cp-music
Platform: UNKNOWN
Classifier: Development Status :: 4 - Beta
Classifier: Intended Audience :: Developers
Classifier: License :: OSI Approved :: MIT License
Classifier: Programming Language :: Python :: 3.6
Classifier: Programming Language :: Python :: 3.7
Requires-Python: >=3.6, <=3.7
